{"metadata":{"total":6806,"page":42,"per_page":100},"results":[{"school.carnegie_basic":-2,"school.region_id":1,"school.zip":"06108","school.school_url":"www.stoneacademy.com","school.name":"Stone Academy-East Hartford","school.carnegie_undergrad":-2,"school.state":"CT","school.locale":13,"school.city":"East Hartford","school.carnegie_size_setting":-2,"school.ownership":3},{"school.carnegie_basic":-2,"school.region_id":5,"school.zip":"70364","school.school_url":"www.unitechtrainingacademy.com","school.name":"Unitech Training Academy-Houma","school.carnegie_undergrad":-2,"school.state":"LA","school.locale":22,"school.city":"Houma","school.carnegie_size_setting":-2,"school.ownership":3},{"school.carnegie_basic":-2,"school.region_id":2,"school.zip":"11357","school.school_url":"www.lincolntech.edu/campus/queens-ny","school.name":"Lincoln Technical Institute-Whitestone","school.carnegie_undergrad":-2,"school.state":"NY","school.locale":11,"school.city":"Whitestone","school.carnegie_size_setting":-2,"school.ownership":3},{"school.carnegie_basic":23,"school.region_id":3,"school.zip":"61108-2513","school.school_url":"https://rasmussen.edu","school.name":"Rasmussen College-Illinois","school.carnegie_undergrad":5,"school.state":"IL","school.locale":12,"school.city":"Rockford","school.carnegie_size_setting":9,"school.ownership":3},{"school.carnegie_basic":-2,"school.region_id":2,"school.zip":"18974","school.school_url":"www.autotraining.edu","school.name":"Automotive Training Center-Warminster","school.carnegie_undergrad":-2,"school.state":"PA","school.locale":21,"school.city":"Warminster","school.carnegie_size_setting":-2,"school.ownership":3},{"school.carnegie_basic":11,"school.region_id":2,"school.zip":"18017","school.school_url":"www.triangle-tech.edu","school.name":"Triangle Tech Inc-Bethlehem","school.carnegie_undergrad":4,"school.state":"PA","school.locale":13,"school.city":"Bethlehem","school.carnegie_size_setting":1,"school.ownership":3},{"school.carnegie_basic":16,"school.region_id":6,"school.zip":"85004","school.school_url":"www.asu.edu/","school.name":"Arizona State University-Downtown Phoenix","school.carnegie_undergrad":13,"school.state":"AZ","school.locale":11,"school.city":"Phoenix","school.carnegie_size_setting":15,"school.ownership":1},{"school.carnegie_basic":-2,"school.region_id":2,"school.zip":"08221","school.school_url":"https://www.harrisschool.edu/campus-locations/linwood-nj/","school.name":"Harris School of Business-Linwood Campus","school.carnegie_undergrad":-2,"school.state":"NJ","school.locale":22,"school.city":"Linwood","school.carnegie_size_setting":-2,"school.ownership":3},{"school.carnegie_basic":18,"school.region_id":2,"school.zip":"17101-2208","school.school_url":"www.HarrisburgU.edu","school.name":"Harrisburg University of Science and Technology","school.carnegie_undergrad":10,"school.state":"PA","school.locale":13,"school.city":"Harrisburg","school.carnegie_size_setting":14,"school.ownership":2},{"school.region_id":4,"school.zip":"666041353","school.school_url":"www.bakeru.edu","school.name":"Baker University School of Nursing","school.state":"KS","school.city":"Topeka","school.ownership":2,"school.carnegie_size_setting":null,"school.carnegie_basic":null,"school.locale":null,"school.carnegie_undergrad":null},{"school.carnegie_basic":-2,"school.region_id":8,"school.zip":"90247","school.school_url":"https://www.uei.edu","school.name":"UEI College-Gardena","school.carnegie_undergrad":-2,"school.state":"CA","school.locale":11,"school.city":"Gardena","school.carnegie_size_setting":-2,"school.ownership":3},{"school.carnegie_basic":-2,"school.region_id":7,"school.zip":"59901","school.school_url":"www.crevierschool.com","school.name":"Crevier's Academy of Cosmetology Arts","school.carnegie_undergrad":-2,"school.state":"MT","school.locale":33,"school.city":"Kalispell","school.carnegie_size_setting":-2,"school.ownership":3},{"school.carnegie_basic":-2,"school.region_id":7,"school.zip":"84074-2093","school.school_url":"www.tooeletech.edu","school.name":"Tooele Technical College","school.carnegie_undergrad":-2,"school.state":"UT","school.locale":41,"school.city":"Tooele","school.carnegie_size_setting":-2,"school.ownership":1},{"school.carnegie_basic":-2,"school.region_id":8,"school.zip":"91730","school.school_url":"thefabschool.edu/","school.name":"The Fab School","school.carnegie_undergrad":-2,"school.state":"CA","school.locale":21,"school.city":"Rancho Cucamonga","school.carnegie_size_setting":-2,"school.ownership":3},{"school.carnegie_basic":-2,"school.region_id":6,"school.zip":"73139","school.school_url":"www.jbsbarbercollege.org","school.name":"JB's Hair Design and Barber College","school.carnegie_undergrad":-2,"school.state":"OK","school.locale":11,"school.city":"Oklahoma City","school.carnegie_size_setting":-2,"school.ownership":3},{"school.carnegie_basic":-2,"school.region_id":2,"school.zip":"17110","school.school_url":"www.divinecrown.com","school.name":"Divine Crown Barber & Beauty Academy","school.carnegie_undergrad":-2,"school.state":"PA","school.locale":21,"school.city":"Harrisburg","school.carnegie_size_setting":-2,"school.ownership":3},{"school.carnegie_basic":-2,"school.region_id":5,"school.zip":"27302-2323","school.school_url":"www.beyondmeasurebarbering.com","school.name":"Beyond Measure Barbering Institute","school.carnegie_undergrad":-2,"school.state":"NC","school.locale":22,"school.city":"Mebane","school.carnegie_size_setting":-2,"school.ownership":3},{"school.carnegie_basic":-2,"school.region_id":5,"school.zip":"33062-1000","school.school_url":"www.beautyanatomy.com","school.name":"McDougle Technical  Institute","school.carnegie_undergrad":-2,"school.state":"FL","school.locale":12,"school.city":"Pompano Beach","school.carnegie_size_setting":-2,"school.ownership":3},{"school.carnegie_basic":-2,"school.region_id":8,"school.zip":"91104","school.school_url":"www.integritycollegeofhealth.net","school.name":"Integrity College of Health","school.carnegie_undergrad":-2,"school.state":"CA","school.locale":12,"school.city":"Pasadena","school.carnegie_size_setting":-2,"school.ownership":3},{"school.carnegie_basic":-2,"school.region_id":5,"school.zip":"40223-1882","school.school_url":"medquestcollege.edu","school.name":"MedQuest College","school.carnegie_undergrad":-2,"school.state":"KY","school.locale":21,"school.city":"Louisville","school.carnegie_size_setting":-2,"school.ownership":3},{"school.carnegie_basic":-2,"school.region_id":8,"school.zip":"92507","school.school_url":"www.cta.edu","school.name":"California Technical Academy","school.carnegie_undergrad":-2,"school.state":"CA","school.locale":11,"school.city":"Riverside","school.carnegie_size_setting":-2,"school.ownership":3},{"school.carnegie_basic":-2,"school.region_id":5,"school.zip":"33012","school.school_url":"MORETECHINSTITUTE.EDU","school.name":"More Tech Institute","school.carnegie_undergrad":-2,"school.state":"FL","school.locale":21,"school.city":"Hialeah","school.carnegie_size_setting":-2,"school.ownership":3},{"school.carnegie_basic":-2,"school.region_id":3,"school.zip":"48334-1300","school.school_url":"paulmitchell.edu/farmingtonhills","school.name":"Paul Mitchell The School-Farmington Hills","school.carnegie_undergrad":-2,"school.state":"MI","school.locale":13,"school.city":"Farmington Hills","school.carnegie_size_setting":-2,"school.ownership":3},{"school.carnegie_basic":-2,"school.region_id":3,"school.zip":"46410-5540","school.school_url":"paulmitchell.edu/merrillville","school.name":"Paul Mitchell the School-Merrillville","school.carnegie_undergrad":-2,"school.state":"IN","school.locale":21,"school.city":"Merrillville","school.carnegie_size_setting":-2,"school.ownership":3},{"school.carnegie_basic":-2,"school.region_id":6,"school.zip":"79602","school.school_url":"neeceescollege.com","school.name":"Neecee's Barber College","school.carnegie_undergrad":-2,"school.state":"TX","school.locale":12,"school.city":"Abilene","school.carnegie_size_setting":-2,"school.ownership":3},{"school.carnegie_basic":-2,"school.region_id":6,"school.zip":"76543-4153","school.school_url":"www.yahwehbeautyacademy.com","school.name":"Yahweh Beauty Academy","school.carnegie_undergrad":-2,"school.state":"TX","school.locale":12,"school.city":"Killeen","school.carnegie_size_setting":-2,"school.ownership":3},{"school.carnegie_basic":-2,"school.region_id":8,"school.zip":"95991","school.school_url":"sutterbeautycollege.com","school.name":"Sutter Beauty College","school.carnegie_undergrad":-2,"school.state":"CA","school.locale":13,"school.city":"Yuba City","school.carnegie_size_setting":-2,"school.ownership":3},{"school.carnegie_basic":-2,"school.region_id":6,"school.zip":"85705","school.school_url":"asismassage.edu/","school.name":"Arizona School of Integrative Studies","school.carnegie_undergrad":-2,"school.state":"AZ","school.locale":11,"school.city":"Tucson","school.carnegie_size_setting":-2,"school.ownership":3},{"school.carnegie_basic":-2,"school.region_id":5,"school.zip":"70122-3808","school.school_url":"www.parkplacebarberschool.com","school.name":"Park Place Premier Barber School","school.carnegie_undergrad":-2,"school.state":"LA","school.locale":11,"school.city":"New Orleans","school.carnegie_size_setting":-2,"school.ownership":3},{"school.carnegie_basic":-2,"school.region_id":8,"school.zip":"95129-5101","school.school_url":"www.tspasanjose.com","school.name":"The Salon Professional Academy-San Jose","school.carnegie_undergrad":-2,"school.state":"CA","school.locale":11,"school.city":"San Jose","school.carnegie_size_setting":-2,"school.ownership":3},{"school.carnegie_basic":-2,"school.region_id":8,"school.zip":"98011-8005","school.school_url":"www.meipn.org","school.name":"Montessori Education Institute of the Pacific Northwest","school.carnegie_undergrad":-2,"school.state":"WA","school.locale":21,"school.city":"Bothell","school.carnegie_size_setting":-2,"school.ownership":2},{"school.carnegie_basic":-2,"school.region_id":5,"school.zip":"23601-1303","school.school_url":"www.luckesbeautyacademy.com","school.name":"Luckes Beauty Academy LLC","school.carnegie_undergrad":-2,"school.state":"VA","school.locale":12,"school.city":"Newport  News","school.carnegie_size_setting":-2,"school.ownership":3},{"school.carnegie_basic":-2,"school.region_id":5,"school.zip":"42303-7757","school.school_url":"www.rosseducation.edu","school.name":"Ross Medical Education Center-Owensboro","school.carnegie_undergrad":-2,"school.state":"KY","school.locale":13,"school.city":"Owensboro","school.carnegie_size_setting":-2,"school.ownership":3},{"school.carnegie_basic":10,"school.region_id":3,"school.zip":"47715-2405","school.school_url":"www.rosseducation.edu","school.name":"Ross Medical Education Center-Evansville","school.carnegie_undergrad":4,"school.state":"IN","school.locale":12,"school.city":"Evansville","school.carnegie_size_setting":1,"school.ownership":3},{"school.carnegie_basic":-2,"school.region_id":2,"school.zip":"17602-3809","school.school_url":"champsbarberschool.com","school.name":"Champ's Barber School","school.carnegie_undergrad":-2,"school.state":"PA","school.locale":13,"school.city":"Lancaster","school.carnegie_size_setting":-2,"school.ownership":3},{"school.carnegie_basic":29,"school.region_id":5,"school.zip":"22182-2734","school.school_url":"www.igu.edu","school.name":"IGlobal University","school.carnegie_undergrad":11,"school.state":"VA","school.locale":21,"school.city":"Vienna","school.carnegie_size_setting":6,"school.ownership":3},{"school.carnegie_basic":-2,"school.region_id":8,"school.zip":"90815-1770","school.school_url":"www.nw.edu","school.name":"North-West College-Long Beach","school.carnegie_undergrad":-2,"school.state":"CA","school.locale":11,"school.city":"Long Beach","school.carnegie_size_setting":-2,"school.ownership":3},{"school.carnegie_basic":-2,"school.region_id":3,"school.zip":"53719-1133","school.school_url":"acupressureschool.com","school.name":"East-West Healing Arts Institute","school.carnegie_undergrad":-2,"school.state":"WI","school.locale":11,"school.city":"Madison","school.carnegie_size_setting":-2,"school.ownership":3},{"school.carnegie_basic":-2,"school.region_id":2,"school.zip":"19138-1324","school.school_url":"www.ptt.edu","school.name":"Philadelphia Technician Training","school.carnegie_undergrad":-2,"school.state":"PA","school.locale":11,"school.city":"Philadelphia","school.carnegie_size_setting":-2,"school.ownership":2},{"school.carnegie_basic":22,"school.region_id":5,"school.zip":"32611","school.school_url":"www.ufonline.ufl.edu","school.name":"University of Florida-Online","school.carnegie_undergrad":5,"school.state":"FL","school.locale":12,"school.city":"Gainesville","school.carnegie_size_setting":9,"school.ownership":1},{"school.carnegie_basic":-2,"school.region_id":2,"school.zip":"11354-6507","school.school_url":"www.acs.edu","school.name":"Alliance Computing Solutions","school.carnegie_undergrad":-2,"school.state":"NY","school.locale":11,"school.city":"Flushing","school.carnegie_size_setting":-2,"school.ownership":3},{"school.carnegie_basic":-2,"school.region_id":5,"school.zip":"33174-2950","school.school_url":"www.itischool.com","school.name":"InterAmerican Technical Institute","school.carnegie_undergrad":-2,"school.state":"FL","school.locale":21,"school.city":"Miami","school.carnegie_size_setting":-2,"school.ownership":3},{"school.carnegie_basic":17,"school.region_id":6,"school.zip":"85040","school.school_url":"https://www.phoenix.edu","school.name":"University of Phoenix-Arizona","school.carnegie_undergrad":11,"school.state":"AZ","school.locale":11,"school.city":"Phoenix","school.carnegie_size_setting":15,"school.ownership":3},{"school.carnegie_basic":22,"school.region_id":7,"school.zip":"80124","school.school_url":"https://www.phoenix.edu","school.name":"University of Phoenix-Colorado","school.carnegie_undergrad":11,"school.state":"CO","school.locale":21,"school.city":"Lone Tree","school.carnegie_size_setting":6,"school.ownership":3},{"school.carnegie_basic":22,"school.region_id":5,"school.zip":"70808","school.school_url":"https://www.phoenix.edu","school.name":"University of Phoenix-Louisiana","school.carnegie_undergrad":0,"school.state":"LA","school.locale":12,"school.city":"Baton Rouge","school.carnegie_size_setting":6,"school.ownership":3},{"school.carnegie_basic":20,"school.region_id":8,"school.zip":"89135","school.school_url":"https://www.phoenix.edu","school.name":"University of Phoenix-Nevada","school.carnegie_undergrad":11,"school.state":"NV","school.locale":21,"school.city":"Las Vegas","school.carnegie_size_setting":6,"school.ownership":3},{"school.carnegie_basic":-2,"school.region_id":5,"school.zip":"32204-4127","school.school_url":"psijax.edu","school.name":"Parisian Spa Institute","school.carnegie_undergrad":-2,"school.state":"FL","school.locale":11,"school.city":"Jacksonville","school.carnegie_size_setting":-2,"school.ownership":3},{"school.carnegie_basic":-2,"school.region_id":3,"school.zip":"44124","school.school_url":"www.labarberiainstitute.com","school.name":"LaBarberia Institute of Hair","school.carnegie_undergrad":-2,"school.state":"OH","school.locale":21,"school.city":"Mayfield Hts","school.carnegie_size_setting":-2,"school.ownership":3},{"school.carnegie_basic":-2,"school.region_id":5,"school.zip":"71109-4124","school.school_url":"www.sts-academy.com","school.name":"Setting the Standard Barbering and Natural Hair Academy","school.carnegie_undergrad":-2,"school.state":"LA","school.locale":12,"school.city":"Shreveport","school.carnegie_size_setting":-2,"school.ownership":3},{"school.carnegie_basic":29,"school.region_id":5,"school.zip":"28273","school.school_url":"https://www.phoenix.edu","school.name":"University of Phoenix-North Carolina","school.carnegie_undergrad":11,"school.state":"NC","school.locale":11,"school.city":"Charlotte","school.carnegie_size_setting":6,"school.ownership":3},{"school.carnegie_basic":29,"school.region_id":6,"school.zip":"77079","school.school_url":"https://www.phoenix.edu","school.name":"University of Phoenix-Texas","school.carnegie_undergrad":11,"school.state":"TX","school.locale":11,"school.city":"Houston","school.carnegie_size_setting":9,"school.ownership":3},{"school.carnegie_basic":22,"school.region_id":2,"school.zip":"19103","school.school_url":"https://www.phoenix.edu","school.name":"University of Phoenix-Pennsylvania","school.carnegie_undergrad":11,"school.state":"PA","school.locale":11,"school.city":"Philadelphia","school.carnegie_size_setting":6,"school.ownership":3},{"school.carnegie_basic":-2,"school.region_id":8,"school.zip":"98101-1596","school.school_url":"tintseattlecosmetologyschool.com","school.name":"Tint School of Makeup & Cosmetology-Seattle","school.carnegie_undergrad":-2,"school.state":"WA","school.locale":11,"school.city":"Seattle","school.carnegie_size_setting":-2,"school.ownership":3},{"school.carnegie_basic":-2,"school.region_id":6,"school.zip":"85284","school.school_url":"avedainstitutephoenix.com","school.name":"Aveda Institute-Phoenix","school.carnegie_undergrad":-2,"school.state":"AZ","school.locale":12,"school.city":"Tempe","school.carnegie_size_setting":-2,"school.ownership":3},{"school.carnegie_basic":-2,"school.region_id":5,"school.zip":"20190","school.school_url":"dsiacademy.edu","school.name":"Dermal Science International Aesthetics and Nail Academy","school.carnegie_undergrad":-2,"school.state":"VA","school.locale":13,"school.city":"Reston","school.carnegie_size_setting":-2,"school.ownership":3},{"school.carnegie_basic":-2,"school.region_id":8,"school.zip":"97504-9998","school.school_url":"www.nwcollege.edu","school.name":"Northwest College-Medford","school.carnegie_undergrad":-2,"school.state":"OR","school.locale":13,"school.city":"Medford","school.carnegie_size_setting":-2,"school.ownership":3},{"school.carnegie_basic":-2,"school.region_id":6,"school.zip":"77063-0000","school.school_url":"houstontrainingschools.net","school.name":"Houston Training Schools-Gessner","school.carnegie_undergrad":-2,"school.state":"TX","school.locale":11,"school.city":"Houston","school.carnegie_size_setting":-2,"school.ownership":3},{"school.carnegie_basic":-2,"school.region_id":5,"school.zip":"30680-2130","school.school_url":"www.newhorizonsmedical.com","school.name":"New Horizons Medical Institute-Winder","school.carnegie_undergrad":-2,"school.state":"GA","school.locale":31,"school.city":"Winder","school.carnegie_size_setting":-2,"school.ownership":3},{"school.carnegie_basic":11,"school.region_id":3,"school.zip":"60610-3132","school.school_url":"CHICAGO.SAE.EDU","school.name":"SAE Institute of Technology-Chicago","school.carnegie_undergrad":4,"school.state":"IL","school.locale":11,"school.city":"Chicago","school.carnegie_size_setting":1,"school.ownership":3},{"school.carnegie_basic":-2,"school.region_id":8,"school.zip":"97232-1315","school.school_url":"www.beaumondeacademy.com","school.name":"Beau Monde Academy of Cosmetology","school.carnegie_undergrad":-2,"school.state":"OR","school.locale":11,"school.city":"Portland","school.carnegie_size_setting":-2,"school.ownership":3},{"school.carnegie_basic":-2,"school.region_id":2,"school.zip":"16046","school.school_url":"fountainofyouthacademy.edu","school.name":"Fountain of Youth Academy of Cosmetology","school.carnegie_undergrad":-2,"school.state":"PA","school.locale":21,"school.city":"Mars","school.carnegie_size_setting":-2,"school.ownership":3},{"school.carnegie_basic":26,"school.region_id":8,"school.zip":"92111","school.school_url":"www.cc-sd.edu","school.name":"California College San Diego","school.carnegie_undergrad":10,"school.state":"CA","school.locale":11,"school.city":"San Diego","school.carnegie_size_setting":6,"school.ownership":2},{"school.carnegie_basic":29,"school.region_id":4,"school.zip":"57701-2823","school.school_url":"www.national.edu/","school.name":"National American University-Harold D. Buckingham Graduate School","school.carnegie_undergrad":0,"school.state":"SD","school.locale":13,"school.city":"Rapid City","school.carnegie_size_setting":18,"school.ownership":3},{"school.carnegie_basic":-2,"school.region_id":6,"school.zip":"86409-2561","school.school_url":"abcollege.edu","school.name":"All Beauty College","school.carnegie_undergrad":-2,"school.state":"AZ","school.locale":33,"school.city":"Kingman","school.carnegie_size_setting":-2,"school.ownership":3},{"school.carnegie_basic":-2,"school.region_id":5,"school.zip":"33405-4813","school.school_url":"www.hi.edu","school.name":"Hollywood Institute of Beauty Careers-West Palm Beach","school.carnegie_undergrad":-2,"school.state":"FL","school.locale":12,"school.city":"West Palm Beach","school.carnegie_size_setting":-2,"school.ownership":3},{"school.region_id":8,"school.zip":"933094523","school.school_url":"www.sjvc.edu/","school.name":"San Joaquin Valley College - Bakersfield","school.state":"CA","school.city":"Bakersfield","school.ownership":3,"school.carnegie_size_setting":null,"school.carnegie_basic":null,"school.locale":null,"school.carnegie_undergrad":null},{"school.region_id":8,"school.zip":"917643616","school.school_url":"sjvc.edu","school.name":"San Joaquin Valley College - Ontario","school.state":"CA","school.city":"Ontario","school.ownership":3,"school.carnegie_size_setting":null,"school.carnegie_basic":null,"school.locale":null,"school.carnegie_undergrad":null},{"school.region_id":8,"school.zip":"923443616","school.school_url":"www.sjvc.edu","school.name":"San Joaquin Valley College - Hesperia","school.state":"CA","school.city":"Hesperia","school.ownership":3,"school.carnegie_size_setting":null,"school.carnegie_basic":null,"school.locale":null,"school.carnegie_undergrad":null},{"school.region_id":8,"school.zip":"919105557","school.school_url":"www.sjvc.edu/","school.name":"San Joaquin Valley College - San Diego","school.state":"CA","school.city":"Chula Vista","school.ownership":3,"school.carnegie_size_setting":null,"school.carnegie_basic":null,"school.locale":null,"school.carnegie_undergrad":null},{"school.region_id":3,"school.zip":"488215004","school.school_url":"www.davenport.edu","school.name":"Davenport University - Treasury Site Dimondale","school.state":"MI","school.city":"Dimondale","school.ownership":2,"school.carnegie_size_setting":null,"school.carnegie_basic":null,"school.locale":null,"school.carnegie_undergrad":null},{"school.region_id":6,"school.zip":"77807","school.school_url":"https://tamhsc.edu/","school.name":"Texas A & M University Health Science Center","school.state":"TX","school.city":"Bryan","school.ownership":1,"school.carnegie_size_setting":null,"school.carnegie_basic":null,"school.locale":null,"school.carnegie_undergrad":null},{"school.region_id":8,"school.zip":"95113","school.school_url":"www.bamasf.com/","school.name":"Bay Area Medical Academy - San Jose Satellite Location","school.state":"CA","school.city":"San Jose","school.ownership":3,"school.carnegie_size_setting":null,"school.carnegie_basic":null,"school.locale":null,"school.carnegie_undergrad":null},{"school.region_id":8,"school.zip":"93301","school.school_url":"www.hdmc.edu","school.name":"High Desert Medical College - Bakerfield","school.state":"CA","school.city":"Bakersfield","school.ownership":3,"school.carnegie_size_setting":null,"school.carnegie_basic":null,"school.locale":null,"school.carnegie_undergrad":null},{"school.region_id":8,"school.zip":"954580000","school.school_url":"www.marymountcalifornia.edu/lakeside/explore","school.name":"Marymount California University - Lakeside Campus","school.state":"CA","school.city":"Lucerne","school.ownership":2,"school.carnegie_size_setting":null,"school.carnegie_basic":null,"school.locale":null,"school.carnegie_undergrad":null},{"school.region_id":3,"school.zip":"488679600","school.school_url":"www.baker.edu","school.name":"Baker College of Owosso","school.state":"MI","school.city":"Owosso","school.ownership":2,"school.carnegie_size_setting":null,"school.carnegie_basic":null,"school.locale":null,"school.carnegie_undergrad":null},{"school.region_id":3,"school.zip":"496019600","school.school_url":"www.baker.edu","school.name":"Baker College of Cadillac","school.state":"MI","school.city":"Cadillac","school.ownership":2,"school.carnegie_size_setting":null,"school.carnegie_basic":null,"school.locale":null,"school.carnegie_undergrad":null},{"school.region_id":3,"school.zip":"494421290","school.school_url":"www.baker.edu","school.name":"Baker College of Muskegon","school.state":"MI","school.city":"Muskegon","school.ownership":2,"school.carnegie_size_setting":null,"school.carnegie_basic":null,"school.locale":null,"school.carnegie_undergrad":null},{"school.region_id":5,"school.zip":"334090000","school.school_url":"www.keiseruniversity.edu/residential/","school.name":"Keiser University - Residential","school.state":"FL","school.city":"West Palm Beach","school.ownership":2,"school.carnegie_size_setting":null,"school.carnegie_basic":null,"school.locale":null,"school.carnegie_undergrad":null},{"school.region_id":5,"school.zip":"392164505","school.school_url":"https://www.umc.edu","school.name":"University of Mississippi Medical Center","school.state":"MS","school.city":"Jackson","school.ownership":1,"school.carnegie_size_setting":null,"school.carnegie_basic":null,"school.locale":null,"school.carnegie_undergrad":null},{"school.region_id":3,"school.zip":"46016","school.school_url":"polytechnic.purdue.edu/anderson","school.name":"Purdue University - Purdue Polytechnic Anderson","school.state":"IN","school.city":"Anderson","school.ownership":1,"school.carnegie_size_setting":null,"school.carnegie_basic":null,"school.locale":null,"school.carnegie_undergrad":null},{"school.region_id":3,"school.zip":"47150","school.school_url":"polytechnic.purdue.edu/new-albany","school.name":"Purdue University - Purdue Polytechnic New Albany","school.state":"IN","school.city":"New Albany","school.ownership":1,"school.carnegie_size_setting":null,"school.carnegie_basic":null,"school.locale":null,"school.carnegie_undergrad":null},{"school.region_id":3,"school.zip":"46904","school.school_url":"polytechnic.purdue.edu/kokomo","school.name":"Purdue University - Purdue Polytechnic Kokomo","school.state":"IN","school.city":"Kokomo","school.ownership":1,"school.carnegie_size_setting":null,"school.carnegie_basic":null,"school.locale":null,"school.carnegie_undergrad":null},{"school.region_id":2,"school.zip":"07102","school.school_url":"relay.edu/location/relay-newark","school.name":"Relay Graduate School of Education - Newark","school.state":"NJ","school.city":"Newark","school.ownership":2,"school.carnegie_size_setting":null,"school.carnegie_basic":null,"school.locale":null,"school.carnegie_undergrad":null},{"school.carnegie_basic":-2,"school.region_id":5,"school.zip":"40229-2862","school.school_url":"www.americancollegeofbarbering.com","school.name":"American College of Barbering","school.carnegie_undergrad":-2,"school.state":"KY","school.locale":11,"school.city":"Louisville","school.carnegie_size_setting":-2,"school.ownership":3},{"school.carnegie_basic":12,"school.region_id":8,"school.zip":"90028-6111","school.school_url":"www.toa.edu","school.name":"Theatre of Arts","school.carnegie_undergrad":4,"school.state":"CA","school.locale":11,"school.city":"Hollywood","school.carnegie_size_setting":1,"school.ownership":3},{"school.carnegie_basic":-2,"school.region_id":6,"school.zip":"75402","school.school_url":"bellacollege.com","school.name":"Bella Cosmetology College","school.carnegie_undergrad":-2,"school.state":"TX","school.locale":32,"school.city":"Greenville","school.carnegie_size_setting":-2,"school.ownership":3},{"school.carnegie_basic":24,"school.region_id":2,"school.zip":"10952-4023","school.school_url":"https://bethmedrashmeoryitzchok.com","school.name":"Beth Medrash Meor Yitzchok","school.carnegie_undergrad":12,"school.state":"NY","school.locale":21,"school.city":"Monsey","school.carnegie_size_setting":6,"school.ownership":2},{"school.carnegie_basic":24,"school.region_id":2,"school.zip":"11230","school.school_url":"https://yeshivasholomshachna.com","school.name":"Yeshiva Sholom Shachna","school.carnegie_undergrad":10,"school.state":"NY","school.locale":11,"school.city":"Brooklyn","school.carnegie_size_setting":8,"school.ownership":2},{"school.carnegie_basic":-2,"school.region_id":6,"school.zip":"77573","school.school_url":"www.kandgbarbercollege.com","school.name":"K & G 5 Star Barber College","school.carnegie_undergrad":-2,"school.state":"TX","school.locale":22,"school.city":"League City","school.carnegie_size_setting":-2,"school.ownership":3},{"school.carnegie_basic":-2,"school.region_id":2,"school.zip":"11769-1650","school.school_url":"www.esboces.org","school.name":"Eastern Suffolk BOCES","school.carnegie_undergrad":-2,"school.state":"NY","school.locale":21,"school.city":"Oakdale","school.carnegie_size_setting":-2,"school.ownership":1},{"school.carnegie_basic":-2,"school.region_id":5,"school.zip":"72756-2028","school.school_url":"www.apcschools.com","school.name":"Academy of Professional Cosmetology","school.carnegie_undergrad":-2,"school.state":"AR","school.locale":13,"school.city":"Rogers","school.carnegie_size_setting":-2,"school.ownership":3},{"school.carnegie_basic":-2,"school.region_id":5,"school.zip":"26241-9527","school.school_url":"rtc.rand.k12.wv.us/","school.name":"Randolph Technical Center","school.carnegie_undergrad":-2,"school.state":"WV","school.locale":33,"school.city":"Elkins","school.carnegie_size_setting":-2,"school.ownership":1},{"school.carnegie_basic":13,"school.region_id":8,"school.zip":"93013-2912","school.school_url":"college.issaonline.edu","school.name":"International Sports Sciences Association","school.carnegie_undergrad":1,"school.state":"CA","school.locale":22,"school.city":"Carpinteria","school.carnegie_size_setting":1,"school.ownership":3},{"school.carnegie_basic":-2,"school.region_id":6,"school.zip":"77065","school.school_url":"www.vocationalnursinginstitute.com","school.name":"The Vocational Nursing Institute Inc","school.carnegie_undergrad":-2,"school.state":"TX","school.locale":11,"school.city":"Houston","school.carnegie_size_setting":-2,"school.ownership":2},{"school.carnegie_basic":-2,"school.region_id":3,"school.zip":"60123-9412","school.school_url":"www.tricociuniversity.edu","school.name":"Tricoci University of Beauty Culture-Elgin","school.carnegie_undergrad":-2,"school.state":"IL","school.locale":12,"school.city":"Elgin","school.carnegie_size_setting":-2,"school.ownership":3},{"school.carnegie_basic":-2,"school.region_id":5,"school.zip":"70125-1056","school.school_url":"www.thechicagoschool.edu/","school.name":"The Chicago School of Professional Psychology at Xavier University of Louisiana","school.carnegie_undergrad":-2,"school.state":"LA","school.locale":11,"school.city":"New Orleans","school.carnegie_size_setting":-2,"school.ownership":2},{"school.carnegie_basic":-2,"school.region_id":6,"school.zip":"77531-3603","school.school_url":"natural-images-bc.com/","school.name":"Natural Images Beauty College","school.carnegie_undergrad":-2,"school.state":"TX","school.locale":23,"school.city":"Clute","school.carnegie_size_setting":-2,"school.ownership":3},{"school.carnegie_basic":-2,"school.region_id":5,"school.zip":"35228-2233","school.school_url":"www.midfieldic.edu","school.name":"Midfield Institute of Cosmetology","school.carnegie_undergrad":-2,"school.state":"AL","school.locale":21,"school.city":"Midfield","school.carnegie_size_setting":-2,"school.ownership":2},{"school.carnegie_basic":29,"school.region_id":8,"school.zip":"91803","school.school_url":"ciam.edu","school.name":"California Institute of Advanced Management","school.carnegie_undergrad":0,"school.state":"CA","school.locale":21,"school.city":"Alhambra","school.carnegie_size_setting":18,"school.ownership":2},{"school.carnegie_basic":-2,"school.region_id":8,"school.zip":"99206","school.school_url":"www.studiobeautyschool.com","school.name":"Studio Beauty School","school.carnegie_undergrad":-2,"school.state":"WA","school.locale":13,"school.city":"Spokane Valley","school.carnegie_size_setting":-2,"school.ownership":3}]}
